gaugefixer/__init__.py
gaugefixer/docstrings.py
gaugefixer/encoder.py
gaugefixer/fixer.py
gaugefixer/models.py
gaugefixer/utils.py
gaugefixer-0.1.0.dist-info/licenses/LICENSE
gaugefixer-0.1.0.dist-info/METADATA
gaugefixer-0.1.0.dist-info/WHEEL
gaugefixer-0.1.0.dist-info/top_level.txt
gaugefixer-0.1.0.dist-info/RECORD
